pierogis-0.4.1.dist-info/entry_points.txt
pierogis-0.4.1.dist-info/RECORD
pierogis-0.4.1.dist-info/LICENSE
pierogis-0.4.1.dist-info/METADATA
pierogis-0.4.1.dist-info/top_level.txt
pierogis-0.4.1.dist-info/WHEEL
pierogis/__init__.py
pierogis/course.py
pierogis/__main__.py
pierogis/algorithms.cpython-37m-i386-linux-gnu.so
pierogis/restaurant.py
pierogis/kitchen/__init__.py
pierogis/kitchen/kitchen.py
pierogis/kitchen/ticket.py
pierogis/kitchen/order.py
pierogis/kitchen/chef.py
pierogis/kitchen/server.py
pierogis/kitchen/menu/__init__.py
pierogis/kitchen/menu/filling.py
pierogis/kitchen/menu/sort_filling.py
pierogis/kitchen/menu/resize_filling.py
pierogis/kitchen/menu/custom_filling.py
pierogis/kitchen/menu/rotate_filling.py
pierogis/kitchen/menu/mmpx_filling.py
pierogis/kitchen/menu/threshold_filling.py
pierogis/kitchen/menu/quantize_filling.py
pierogis/kitchen/menu/crop_filling.py
pierogis/ingredients/__init__.py
pierogis/ingredients/sort.py
pierogis/ingredients/dish.py
pierogis/ingredients/crop.py
pierogis/ingredients/recipe.py
pierogis/ingredients/pierogi.py
pierogis/ingredients/flip.py
pierogis/ingredients/mmpx.py
pierogis/ingredients/rotate.py
pierogis/ingredients/quantize.py
pierogis/ingredients/ingredient.py
pierogis/ingredients/resize.py
pierogis/ingredients/seasonings/__init__.py
pierogis/ingredients/seasonings/rectangle.py
pierogis/ingredients/seasonings/seasoning.py
pierogis/ingredients/seasonings/cartography.py
pierogis/ingredients/seasonings/threshold.py
