Metadata-Version: 2.1
Name: pierogis
Version: 0.4.1
Summary: image and animation processing framework
Home-page: https://github.com/pierogis/pierogis
Author: pierogis-live
Author-email: admin@pierogis.live
License: UNKNOWN
Platform: UNKNOWN
License-File: LICENSE
Requires-Dist: Pillow (>=8.0.1)
Requires-Dist: numpy (>=1.20.1)
Requires-Dist: imageio (>=2.9.0)
Requires-Dist: imageio-ffmpeg (>=0.4.3)
Requires-Dist: natsort (>=7.1.1)
Requires-Dist: rich (==10.1.0)
Provides-Extra: dev
Requires-Dist: setuptools-scm (>=6.0.1) ; extra == 'dev'
Requires-Dist: setuptools-rust ; extra == 'dev'
Requires-Dist: wheel ; extra == 'dev'
Requires-Dist: pytest ; extra == 'dev'
